[
	{
		"ele" : 90,
		"dist" : 0.1
	},
	{
		"ele" : 86,
		"dist" : 0.1
	},
	{
		"ele" : 84,
		"dist" : 0.1
	},
	{
		"ele" : 81,
		"dist" : 0.2
	},
	{
		"ele" : 80,
		"dist" : 0.3
	},
	{
		"ele" : 80,
		"dist" : 0.5
	},
	{
		"ele" : 80,
		"dist" : 0.6
	},
	{
		"ele" : 80,
		"dist" : 0.6
	},
	{
		"ele" : 80,
		"dist" : 0.7
	},
	{
		"ele" : 80,
		"dist" : 0.8
	},
	{
		"ele" : 80,
		"dist" : 0.9
	},
	{
		"ele" : 79,
		"dist" : 0.9
	},
	{
		"ele" : 79,
		"dist" : 1
	},
	{
		"ele" : 79,
		"dist" : 1
	},
	{
		"ele" : 81,
		"dist" : 1
	},
	{
		"ele" : 82,
		"dist" : 1.1
	},
	{
		"ele" : 85,
		"dist" : 1.1
	},
	{
		"ele" : 84,
		"dist" : 1.2
	},
	{
		"ele" : 97,
		"dist" : 1.3
	},
	{
		"ele" : 105,
		"dist" : 1.3
	},
	{
		"ele" : 116,
		"dist" : 1.3
	},
	{
		"ele" : 121,
		"dist" : 1.4
	},
	{
		"ele" : 120,
		"dist" : 1.4
	},
	{
		"ele" : 119,
		"dist" : 1.4
	},
	{
		"ele" : 111,
		"dist" : 1.5
	},
	{
		"ele" : 108,
		"dist" : 1.5
	},
	{
		"ele" : 102,
		"dist" : 1.6
	},
	{
		"ele" : 100,
		"dist" : 1.6
	},
	{
		"ele" : 96,
		"dist" : 1.7
	},
	{
		"ele" : 93,
		"dist" : 1.7
	},
	{
		"ele" : 90,
		"dist" : 1.8
	},
	{
		"ele" : 95,
		"dist" : 1.8
	},
	{
		"ele" : 100,
		"dist" : 1.8
	},
	{
		"ele" : 104,
		"dist" : 1.9
	},
	{
		"ele" : 110,
		"dist" : 1.9
	},
	{
		"ele" : 119,
		"dist" : 2
	},
	{
		"ele" : 127,
		"dist" : 2
	},
	{
		"ele" : 133,
		"dist" : 2.1
	},
	{
		"ele" : 137,
		"dist" : 2.1
	},
	{
		"ele" : 145,
		"dist" : 2.2
	},
	{
		"ele" : 151,
		"dist" : 2.3
	},
	{
		"ele" : 158,
		"dist" : 2.4
	},
	{
		"ele" : 158,
		"dist" : 2.4
	},
	{
		"ele" : 157,
		"dist" : 2.4
	},
	{
		"ele" : 159,
		"dist" : 2.5
	},
	{
		"ele" : 156,
		"dist" : 2.6
	},
	{
		"ele" : 157,
		"dist" : 2.6
	},
	{
		"ele" : 150,
		"dist" : 2.7
	},
	{
		"ele" : 146,
		"dist" : 2.7
	},
	{
		"ele" : 145,
		"dist" : 2.7
	},
	{
		"ele" : 135,
		"dist" : 2.8
	},
	{
		"ele" : 122,
		"dist" : 2.9
	},
	{
		"ele" : 108,
		"dist" : 2.9
	},
	{
		"ele" : 102,
		"dist" : 3
	},
	{
		"ele" : 97,
		"dist" : 3
	},
	{
		"ele" : 96,
		"dist" : 3.1
	}
]